dicom_qr/__init__.py
dicom_qr/console_output.py
dicom_qr/contexts.py
dicom_qr/database.py
dicom_qr/deid_anonymizer.dicom
dicom_qr/deid_anonymizer.py
dicom_qr/deid_filter.dicom
dicom_qr/deident.py
dicom_qr/deident_tools.py
dicom_qr/dispatch.py
dicom_qr/download.py
dicom_qr/echo.py
dicom_qr/errors.py
dicom_qr/logger.py
dicom_qr/py.typed
dicom_qr/query.py
dicom_qr/retrieve.py
dicom_qr/retrieve_utils.py
dicom_qr/scp.py
dicom_qr/search.py
dicom_qr/settings.py
dicom_qr/storage_classes.py
dicom_qr/dicom_web/__init__.py
dicom_qr/dicom_web/qido_rs.py
dicom_qr/dicom_web/stow_rs.py
dicom_qr/dicom_web/wado_rs.py
dicom_qr/dimse/__init__.py
dicom_qr/dimse/query_c_find.py
dicom_qr/dimse/retrieve_c_get.py
dicom_qr/dimse/retrieve_c_move.py
dicom_qr/dimse/store_c_store.py
dicom_qr/tui/__init__.py
dicom_qr/tui/__main__.py
dicom_qr/tui/download_screen.py
dicom_qr/tui/pacs_app.py
dicom_qr/tui/pacs_app.tcss
dicom_qr/tui/search_terms.py
dicom_qr/tui/series.py
dicom_qr/tui/settings.py
dicom_qr/tui/studies.py
dicom_qr/tui/worklist_widget.py
dicom_qr-0.2.2.dist-info/METADATA
dicom_qr-0.2.2.dist-info/WHEEL
dicom_qr-0.2.2.dist-info/entry_points.txt
dicom_qr-0.2.2.dist-info/RECORD
