Metadata-Version: 2.4
Name: dicom_qr
Version: 0.2.2
Summary: Tool for retrieving data from a PACS
Project-URL: homepage, https://lkeb.nl
Project-URL: repository, https://git.lumc.nl/lkeb/lkeb_it-infra/dicom_qr
Project-URL: documentation, https://lkeb.github.io/docs/dicom-qr/
Author-email: Patrick de Koning <pjhdekoning@lumc.nl>
License: MIT
Keywords: DICOM,PACS
Classifier: Development Status :: 4 - Beta
Classifier: Environment :: Console
Classifier: Intended Audience :: Developers
Classifier: Intended Audience :: Healthcare Industry
Classifier: Intended Audience :: Science/Research
Classifier: License :: OSI Approved :: MIT License
Classifier: Natural Language :: English
Classifier: Operating System :: OS Independent
Classifier: Programming Language :: Python :: 3.11
Classifier: Topic :: Scientific/Engineering :: Bio-Informatics
Classifier: Topic :: Scientific/Engineering :: Medical Science Apps.
Requires-Python: >=3.11
Requires-Dist: deid
Requires-Dist: devtools
Requires-Dist: dicomweb-client>=0.60.1
Requires-Dist: jsonpickle
Requires-Dist: lkeb-progress
Requires-Dist: loguru
Requires-Dist: pandas
Requires-Dist: pathvalidate
Requires-Dist: pydantic
Requires-Dist: pydantic-settings
Requires-Dist: pynetdicom
Requires-Dist: python-dateutil
Requires-Dist: rich
Requires-Dist: simpleitk
Requires-Dist: typer
Requires-Dist: xmltodict
Provides-Extra: tui
Requires-Dist: textual; extra == 'tui'
Requires-Dist: textual-file-viewer; extra == 'tui'
Requires-Dist: textual-fspicker; extra == 'tui'
Requires-Dist: textual-image; extra == 'tui'
Requires-Dist: textual-sortable-datatable; extra == 'tui'
